server.py
boxlite_mcp-0.2.5.dist-info/METADATA
boxlite_mcp-0.2.5.dist-info/WHEEL
boxlite_mcp-0.2.5.dist-info/entry_points.txt
boxlite_mcp-0.2.5.dist-info/licenses/LICENSE
boxlite_mcp-0.2.5.dist-info/RECORD
