Metadata-Version: 2.4
Name: boxlite-mcp
Version: 0.2.5
Summary: MCP server providing computer use capabilities through an isolated sandbox environment
License-Expression: Apache-2.0
License-File: LICENSE
Keywords: automation,computer-use,isolation,mcp,sandbox
Classifier: Development Status :: 3 - Alpha
Classifier: Intended Audience :: Developers
Classifier: License :: OSI Approved :: Apache Software License
Classifier: Programming Language :: Python :: 3
Classifier: Programming Language :: Python :: 3.10
Classifier: Programming Language :: Python :: 3.11
Classifier: Programming Language :: Python :: 3.12
Classifier: Programming Language :: Python :: 3.13
Requires-Python: >=3.10
Requires-Dist: anyio>=4.0.0
Requires-Dist: boxlite>=0.3.2
Requires-Dist: httpx<1.0,>=0.27.0
Requires-Dist: mcp>=1.0.0
Provides-Extra: dev
Requires-Dist: pytest-asyncio>=0.21.0; extra == 'dev'
Requires-Dist: pytest>=7.0.0; extra == 'dev'
Requires-Dist: ruff>=0.1.0; extra == 'dev'
